{
    "Ar36": {
        "error": 0.00018639554105011281, 
        "filter_outliers_dict": {
            "filter_outliers": true, 
            "iterations": 1, 
            "std_devs": 2
        }, 
        "fit": "Parabolic", 
        "fn": 382, 
        "include_baseline_error": false, 
        "n": 400, 
        "value": 0.0012628426145071371
    }, 
    "Ar37": {
        "error": 0.011712719228566969, 
        "filter_outliers_dict": {
            "filter_outliers": true, 
            "iterations": 1, 
            "std_devs": 2
        }, 
        "fit": "Linear", 
        "fn": 381, 
        "include_baseline_error": false, 
        "n": 400, 
        "value": -0.5255882580266801
    }, 
    "Ar38": {
        "error": 0.02284386327148749, 
        "filter_outliers_dict": {
            "filter_outliers": true, 
            "iterations": 1, 
            "std_devs": 2
        }, 
        "fit": "Parabolic", 
        "fn": 382, 
        "include_baseline_error": false, 
        "n": 400, 
        "value": -0.11056740483070568
    }, 
    "Ar39": {
        "error": 0.02631870295371346, 
        "filter_outliers_dict": {
            "filter_outliers": true, 
            "iterations": 1, 
            "std_devs": 2
        }, 
        "fit": "Parabolic", 
        "fn": 385, 
        "include_baseline_error": false, 
        "n": 400, 
        "value": -0.022459696875264848
    }, 
    "Ar40": {
        "error": 0.020141436319871565, 
        "filter_outliers_dict": {
            "filter_outliers": true, 
            "iterations": 1, 
            "std_devs": 2
        }, 
        "fit": "Parabolic", 
        "fn": 382, 
        "include_baseline_error": false, 
        "n": 400, 
        "value": 0.34941832286225744
    }, 
    "reviewed": true
}